webtech/__burp__.py
webtech/__init__.py
webtech/__main__.py
webtech/__version__.py
webtech/apps.json
webtech/database.py
webtech/encoder.py
webtech/parser.py
webtech/target.py
webtech/ua.txt
webtech/utils.py
webtech/webtech.json
webtech/webtech.py
webtech-1.3.3.dist-info/LICENSE
webtech-1.3.3.dist-info/METADATA
webtech-1.3.3.dist-info/WHEEL
webtech-1.3.3.dist-info/entry_points.txt
webtech-1.3.3.dist-info/top_level.txt
webtech-1.3.3.dist-info/RECORD
