Metadata-Version: 2.1
Name: webtech
Version: 1.3.3
Summary: Identify technologies used on websites
Home-page: https://github.com/ShielderSec/webtech
Author: thezero, polict
Author-email: info@shielder.it
License: GPLv3
Classifier: License :: OSI Approved :: GNU General Public License v3 (GPLv3)
Classifier: Programming Language :: Python
Classifier: Programming Language :: Python :: 3
Classifier: Programming Language :: Python :: 3.6
Classifier: Programming Language :: Python :: Implementation :: CPython
Classifier: Programming Language :: Python :: Implementation :: PyPy
Classifier: Environment :: Console
Classifier: Operating System :: OS Independent
Classifier: Topic :: Internet :: WWW/HTTP
Classifier: Topic :: Security
Requires-Python: >=2.7.0
License-File: LICENSE
Requires-Dist: requests
